<?xml version="1.0" encoding="UTF-8" standalone="yes"?>
<p:sld xmlns:a="http://schemas.openxmlformats.org/drawingml/2006/main" xmlns:r="http://schemas.openxmlformats.org/officeDocument/2006/relationships" xmlns:p="http://schemas.openxmlformats.org/presentationml/2006/main"><p:cSld><p:spTree><p:nvGrpSpPr><p:cNvPr id="1" name=""/><p:cNvGrpSpPr/><p:nvPr/></p:nvGrpSpPr><p:grpSpPr><a:xfrm><a:off x="0" y="0"/><a:ext cx="0" cy="0"/><a:chOff x="0" y="0"/><a:chExt cx="0" cy="0"/></a:xfrm></p:grpSpPr><p:sp><p:nvSpPr><p:cNvPr id="2" name="矩形 1"><a:extLst><a:ext uri="{FF2B5EF4-FFF2-40B4-BE49-F238E27FC236}"><a16:creationId xmlns:a16="http://schemas.microsoft.com/office/drawing/2014/main" id="{EC356C92-CBCC-4C98-859B-E723744E6832}"/></a:ext></a:extLst></p:cNvPr><p:cNvSpPr/><p:nvPr/></p:nvSpPr><p:spPr><a:xfrm><a:off x="0" y="0"/><a:ext cx="12192000" cy="6858000"/></a:xfrm><a:prstGeom prst="rect"><a:avLst/></a:prstGeom><a:solidFill><a:srgbClr val="FFFFFF"/></a:solidFill><a:ln w="12700" cap="flat" cmpd="sng" algn="ctr"><a:noFill/><a:prstDash val="solid"/><a:miter lim="800000"/></a:ln><a:effectLst/><a:extLst><a:ext uri="{91240B29-F687-4F45-9708-019B960494DF}"><a14:hiddenLine xmlns:a14="http://schemas.microsoft.com/office/drawing/2010/main" w="12700" cap="flat" cmpd="sng" algn="ctr"><a:solidFill><a:schemeClr val="accent1"><a:shade val="50000"/></a:schemeClr></a:solidFill><a:prstDash val="solid"/><a:miter lim="800000"/></a14:hiddenLine></a:ext></a:extLst></p:spPr><p:style><a:lnRef idx="2"><a:schemeClr val="accent1"><a:shade val="50000"/></a:schemeClr></a:lnRef><a:fillRef idx="1"><a:schemeClr val="accent1"/></a:fillRef><a:effectRef idx="0"><a:schemeClr val="accent1"/></a:effectRef><a:fontRef idx="minor"><a:schemeClr val="lt1"/></a:fontRef></p:style><p:txBody><a:bodyPr rtlCol="0" anchor="ctr"/><a:lstStyle/><a:p><a:pPr algn="ctr"/><a:endParaRPr lang="zh-CN" altLang="en-US"/></a:p></p:txBody></p:sp><p:sp><p:nvSpPr><p:cNvPr id="3" name="矩形 2"><a:extLst><a:ext uri="{FF2B5EF4-FFF2-40B4-BE49-F238E27FC236}"><a16:creationId xmlns:a16="http://schemas.microsoft.com/office/drawing/2014/main" id="{847E08AB-090B-4BA1-B8D5-7FA5A8B4CAC8}"/></a:ext></a:extLst></p:cNvPr><p:cNvSpPr/><p:nvPr/></p:nvSpPr><p:spPr><a:xfrm><a:off x="0" y="0"/><a:ext cx="4389120" cy="6858000"/></a:xfrm><a:prstGeom prst="rect"><a:avLst/></a:prstGeom><a:solidFill><a:srgbClr val="1B3355"/></a:solidFill><a:ln w="12700" cap="flat" cmpd="sng" algn="ctr"><a:noFill/><a:prstDash val="solid"/><a:miter lim="800000"/></a:ln><a:effectLst/><a:extLst><a:ext uri="{91240B29-F687-4F45-9708-019B960494DF}"><a14:hiddenLine xmlns:a14="http://schemas.microsoft.com/office/drawing/2010/main" w="12700" cap="flat" cmpd="sng" algn="ctr"><a:solidFill><a:schemeClr val="accent1"><a:shade val="50000"/></a:schemeClr></a:solidFill><a:prstDash val="solid"/><a:miter lim="800000"/></a14:hiddenLine></a:ext></a:extLst></p:spPr><p:style><a:lnRef idx="2"><a:schemeClr val="accent1"><a:shade val="50000"/></a:schemeClr></a:lnRef><a:fillRef idx="1"><a:schemeClr val="accent1"/></a:fillRef><a:effectRef idx="0"><a:schemeClr val="accent1"/></a:effectRef><a:fontRef idx="minor"><a:schemeClr val="lt1"/></a:fontRef></p:style><p:txBody><a:bodyPr rtlCol="0" anchor="ctr"/><a:lstStyle/><a:p><a:pPr algn="ctr"/><a:endParaRPr lang="zh-CN" altLang="en-US"/></a:p></p:txBody></p:sp><p:sp><p:nvSpPr><p:cNvPr id="4" name="矩形 3"><a:extLst><a:ext uri="{FF2B5EF4-FFF2-40B4-BE49-F238E27FC236}"><a16:creationId xmlns:a16="http://schemas.microsoft.com/office/drawing/2014/main" id="{1B3BE2DB-7E18-47FE-A21F-FDD5F4430D37}"/></a:ext></a:extLst></p:cNvPr><p:cNvSpPr/><p:nvPr/></p:nvSpPr><p:spPr><a:xfrm><a:off x="4389120" y="0"/><a:ext cx="7802880" cy="152400"/></a:xfrm><a:prstGeom prst="rect"><a:avLst/></a:prstGeom><a:solidFill><a:srgbClr val="2A8FA0"/></a:solidFill><a:ln w="12700" cap="flat" cmpd="sng" algn="ctr"><a:noFill/><a:prstDash val="solid"/><a:miter lim="800000"/></a:ln><a:effectLst/><a:extLst><a:ext uri="{91240B29-F687-4F45-9708-019B960494DF}"><a14:hiddenLine xmlns:a14="http://schemas.microsoft.com/office/drawing/2010/main" w="12700" cap="flat" cmpd="sng" algn="ctr"><a:solidFill><a:schemeClr val="accent1"><a:shade val="50000"/></a:schemeClr></a:solidFill><a:prstDash val="solid"/><a:miter lim="800000"/></a14:hiddenLine></a:ext></a:extLst></p:spPr><p:style><a:lnRef idx="2"><a:schemeClr val="accent1"><a:shade val="50000"/></a:schemeClr></a:lnRef><a:fillRef idx="1"><a:schemeClr val="accent1"/></a:fillRef><a:effectRef idx="0"><a:schemeClr val="accent1"/></a:effectRef><a:fontRef idx="minor"><a:schemeClr val="lt1"/></a:fontRef></p:style><p:txBody><a:bodyPr rtlCol="0" anchor="ctr"/><a:lstStyle/><a:p><a:pPr algn="ctr"/><a:endParaRPr lang="zh-CN" altLang="en-US"/></a:p></p:txBody></p:sp><p:sp><p:nvSpPr><p:cNvPr id="5" name="文本框 4"><a:extLst><a:ext uri="{FF2B5EF4-FFF2-40B4-BE49-F238E27FC236}"><a16:creationId xmlns:a16="http://schemas.microsoft.com/office/drawing/2014/main" id="{AF32855F-5EC9-4D08-BE50-D51A97317637}"/></a:ext></a:extLst></p:cNvPr><p:cNvSpPr txBox="1"/><p:nvPr/></p:nvSpPr><p:spPr><a:xfrm><a:off x="787400" y="990600"/><a:ext cx="2794000" cy="518091"/></a:xfrm><a:prstGeom prst="rect"><a:avLst/></a:prstGeom><a:noFill/></p:spPr><p:txBody><a:bodyPr vert="horz" lIns="76200" tIns="50800" rIns="76200" bIns="50800" rtlCol="0"><a:spAutoFit/></a:bodyPr><a:lstStyle/><a:p><a:r><a:rPr lang="zh-CN" altLang="en-US" sz="2700" b="1"><a:solidFill><a:srgbClr val="DDAA48"/></a:solidFill><a:latin typeface="Microsoft YaHei" panose="020B0503020204020204" pitchFamily="34" charset="-122"/></a:rPr><a:t>中期报告</a:t></a:r></a:p></p:txBody></p:sp><p:sp><p:nvSpPr><p:cNvPr id="6" name="文本框 5"><a:extLst><a:ext uri="{FF2B5EF4-FFF2-40B4-BE49-F238E27FC236}"><a16:creationId xmlns:a16="http://schemas.microsoft.com/office/drawing/2014/main" id="{7F2638BB-3F3C-41F2-990E-815FCDEB6216}"/></a:ext></a:extLst></p:cNvPr><p:cNvSpPr txBox="1"/><p:nvPr/></p:nvSpPr><p:spPr><a:xfrm><a:off x="812800" y="1549400"/><a:ext cx="2794000" cy="287258"/></a:xfrm><a:prstGeom prst="rect"><a:avLst/></a:prstGeom><a:noFill/></p:spPr><p:txBody><a:bodyPr vert="horz" lIns="76200" tIns="50800" rIns="76200" bIns="50800" rtlCol="0"><a:spAutoFit/></a:bodyPr><a:lstStyle/><a:p><a:r><a:rPr lang="en-US" altLang="zh-CN" sz="1200"><a:solidFill><a:srgbClr val="FFFFFF"/></a:solidFill><a:latin typeface="Microsoft YaHei" panose="020B0503020204020204" pitchFamily="34" charset="-122"/></a:rPr><a:t>MIDTERM REPORT</a:t></a:r><a:endParaRPr lang="zh-CN" altLang="en-US" sz="1200"><a:solidFill><a:srgbClr val="FFFFFF"/></a:solidFill><a:latin typeface="Microsoft YaHei" panose="020B0503020204020204" pitchFamily="34" charset="-122"/></a:endParaRPr></a:p></p:txBody></p:sp><p:sp><p:nvSpPr><p:cNvPr id="7" name="文本框 6"><a:extLst><a:ext uri="{FF2B5EF4-FFF2-40B4-BE49-F238E27FC236}"><a16:creationId xmlns:a16="http://schemas.microsoft.com/office/drawing/2014/main" id="{5F3A16D5-B022-41E7-86B7-E518D18FAAE6}"/></a:ext></a:extLst></p:cNvPr><p:cNvSpPr txBox="1"/><p:nvPr/></p:nvSpPr><p:spPr><a:xfrm><a:off x="4998720" y="1422400"/><a:ext cx="7112000" cy="1056700"/></a:xfrm><a:prstGeom prst="rect"><a:avLst/></a:prstGeom><a:noFill/></p:spPr><p:txBody><a:bodyPr vert="horz" lIns="76200" tIns="50800" rIns="76200" bIns="50800" rtlCol="0"><a:spAutoFit/></a:bodyPr><a:lstStyle/><a:p><a:r><a:rPr lang="zh-CN" altLang="en-US" sz="3100" b="1"><a:solidFill><a:srgbClr val="1B3355"/></a:solidFill><a:latin typeface="Microsoft YaHei" panose="020B0503020204020204" pitchFamily="34" charset="-122"/></a:rPr><a:t>基于智能体的多机器人算力互联网调度研究</a:t></a:r></a:p></p:txBody></p:sp><p:sp><p:nvSpPr><p:cNvPr id="8" name="文本框 7"><a:extLst><a:ext uri="{FF2B5EF4-FFF2-40B4-BE49-F238E27FC236}"><a16:creationId xmlns:a16="http://schemas.microsoft.com/office/drawing/2014/main" id="{77F99FF5-B6BA-4E9B-8BCF-D0818C24B2C3}"/></a:ext></a:extLst></p:cNvPr><p:cNvSpPr txBox="1"/><p:nvPr/></p:nvSpPr><p:spPr><a:xfrm><a:off x="5049520" y="2730500"/><a:ext cx="6858000" cy="333425"/></a:xfrm><a:prstGeom prst="rect"><a:avLst/></a:prstGeom><a:noFill/></p:spPr><p:txBody><a:bodyPr vert="horz" lIns="76200" tIns="50800" rIns="76200" bIns="50800" rtlCol="0"><a:spAutoFit/></a:bodyPr><a:lstStyle/><a:p><a:r><a:rPr lang="zh-CN" altLang="en-US" sz="1500"><a:solidFill><a:srgbClr val="5F6F82"/></a:solidFill><a:latin typeface="Microsoft YaHei" panose="020B0503020204020204" pitchFamily="34" charset="-122"/></a:rPr><a:t>基于强化学习、图注意力网络与动态奖励机制的阶段性研究进展</a:t></a:r></a:p></p:txBody></p:sp><p:sp><p:nvSpPr><p:cNvPr id="9" name="矩形 8"><a:extLst><a:ext uri="{FF2B5EF4-FFF2-40B4-BE49-F238E27FC236}"><a16:creationId xmlns:a16="http://schemas.microsoft.com/office/drawing/2014/main" id="{3EA13E4C-50B8-48B5-A354-600EE57140E5}"/></a:ext></a:extLst></p:cNvPr><p:cNvSpPr/><p:nvPr/></p:nvSpPr><p:spPr><a:xfrm><a:off x="5074920" y="3429000"/><a:ext cx="1524000" cy="63500"/></a:xfrm><a:prstGeom prst="rect"><a:avLst/></a:prstGeom><a:solidFill><a:srgbClr val="2A8FA0"/></a:solidFill><a:ln w="12700" cap="flat" cmpd="sng" algn="ctr"><a:noFill/><a:prstDash val="solid"/><a:miter lim="800000"/></a:ln><a:effectLst/><a:extLst><a:ext uri="{91240B29-F687-4F45-9708-019B960494DF}"><a14:hiddenLine xmlns:a14="http://schemas.microsoft.com/office/drawing/2010/main" w="12700" cap="flat" cmpd="sng" algn="ctr"><a:solidFill><a:schemeClr val="accent1"><a:shade val="50000"/></a:schemeClr></a:solidFill><a:prstDash val="solid"/><a:miter lim="800000"/></a14:hiddenLine></a:ext></a:extLst></p:spPr><p:style><a:lnRef idx="2"><a:schemeClr val="accent1"><a:shade val="50000"/></a:schemeClr></a:lnRef><a:fillRef idx="1"><a:schemeClr val="accent1"/></a:fillRef><a:effectRef idx="0"><a:schemeClr val="accent1"/></a:effectRef><a:fontRef idx="minor"><a:schemeClr val="lt1"/></a:fontRef></p:style><p:txBody><a:bodyPr rtlCol="0" anchor="ctr"/><a:lstStyle/><a:p><a:pPr algn="ctr"/><a:endParaRPr lang="zh-CN" altLang="en-US"/></a:p></p:txBody></p:sp><p:sp><p:nvSpPr><p:cNvPr id="10" name="文本框 9"><a:extLst><a:ext uri="{FF2B5EF4-FFF2-40B4-BE49-F238E27FC236}"><a16:creationId xmlns:a16="http://schemas.microsoft.com/office/drawing/2014/main" id="{746A32F5-3C30-415A-B8A9-D73F3C78796E}"/></a:ext></a:extLst></p:cNvPr><p:cNvSpPr txBox="1"/><p:nvPr/></p:nvSpPr><p:spPr><a:xfrm><a:off x="5074920" y="4127500"/><a:ext cx="3302000" cy="318036"/></a:xfrm><a:prstGeom prst="rect"><a:avLst/></a:prstGeom><a:noFill/></p:spPr><p:txBody><a:bodyPr vert="horz" lIns="76200" tIns="50800" rIns="76200" bIns="50800" rtlCol="0"><a:spAutoFit/></a:bodyPr><a:lstStyle/><a:p><a:r><a:rPr lang="zh-CN" altLang="en-US" sz="1400"><a:solidFill><a:srgbClr val="1B3355"/></a:solidFill><a:latin typeface="Microsoft YaHei" panose="020B0503020204020204" pitchFamily="34" charset="-122"/></a:rPr><a:t>答辩人：王星宇</a:t></a:r></a:p></p:txBody></p:sp><p:sp><p:nvSpPr><p:cNvPr id="11" name="文本框 10"><a:extLst><a:ext uri="{FF2B5EF4-FFF2-40B4-BE49-F238E27FC236}"><a16:creationId xmlns:a16="http://schemas.microsoft.com/office/drawing/2014/main" id="{8516D263-A3E0-4C69-85FC-10E8E6C42825}"/></a:ext></a:extLst></p:cNvPr><p:cNvSpPr txBox="1"/><p:nvPr/></p:nvSpPr><p:spPr><a:xfrm><a:off x="5074920" y="4495800"/><a:ext cx="3302000" cy="318036"/></a:xfrm><a:prstGeom prst="rect"><a:avLst/></a:prstGeom><a:noFill/></p:spPr><p:txBody><a:bodyPr vert="horz" lIns="76200" tIns="50800" rIns="76200" bIns="50800" rtlCol="0"><a:spAutoFit/></a:bodyPr><a:lstStyle/><a:p><a:r><a:rPr lang="zh-CN" altLang="en-US" sz="1400"><a:solidFill><a:srgbClr val="1B3355"/></a:solidFill><a:latin typeface="Microsoft YaHei" panose="020B0503020204020204" pitchFamily="34" charset="-122"/></a:rPr><a:t>导师：栗蔚</a:t></a:r></a:p></p:txBody></p:sp><p:sp><p:nvSpPr><p:cNvPr id="12" name="文本框 11"><a:extLst><a:ext uri="{FF2B5EF4-FFF2-40B4-BE49-F238E27FC236}"><a16:creationId xmlns:a16="http://schemas.microsoft.com/office/drawing/2014/main" id="{99FACBB1-079E-4218-B715-EFF5888B2878}"/></a:ext></a:extLst></p:cNvPr><p:cNvSpPr txBox="1"/><p:nvPr/></p:nvSpPr><p:spPr><a:xfrm><a:off x="5074920" y="4864100"/><a:ext cx="3810000" cy="318036"/></a:xfrm><a:prstGeom prst="rect"><a:avLst/></a:prstGeom><a:noFill/></p:spPr><p:txBody><a:bodyPr vert="horz" lIns="76200" tIns="50800" rIns="76200" bIns="50800" rtlCol="0"><a:spAutoFit/></a:bodyPr><a:lstStyle/><a:p><a:r><a:rPr lang="zh-CN" altLang="en-US" sz="1400"><a:solidFill><a:srgbClr val="1B3355"/></a:solidFill><a:latin typeface="Microsoft YaHei" panose="020B0503020204020204" pitchFamily="34" charset="-122"/></a:rPr><a:t>课题单位：中国信息通信研究院</a:t></a:r></a:p></p:txBody></p:sp><p:sp><p:nvSpPr><p:cNvPr id="13" name="文本框 12"><a:extLst><a:ext uri="{FF2B5EF4-FFF2-40B4-BE49-F238E27FC236}"><a16:creationId xmlns:a16="http://schemas.microsoft.com/office/drawing/2014/main" id="{BEA5246A-2775-45B6-AABD-3CEC8B0C75BA}"/></a:ext></a:extLst></p:cNvPr><p:cNvSpPr txBox="1"/><p:nvPr/></p:nvSpPr><p:spPr><a:xfrm><a:off x="10350500" y="5969000"/><a:ext cx="1143000" cy="318036"/></a:xfrm><a:prstGeom prst="rect"><a:avLst/></a:prstGeom><a:noFill/></p:spPr><p:txBody><a:bodyPr vert="horz" lIns="76200" tIns="50800" rIns="76200" bIns="50800" rtlCol="0"><a:spAutoFit/></a:bodyPr><a:lstStyle/><a:p><a:pPr algn="r"/><a:r><a:rPr lang="en-US" altLang="zh-CN" sz="1400" b="1"><a:solidFill><a:srgbClr val="2A8FA0"/></a:solidFill><a:latin typeface="Microsoft YaHei" panose="020B0503020204020204" pitchFamily="34" charset="-122"/></a:rPr><a:t>2026.05</a:t></a:r><a:endParaRPr lang="zh-CN" altLang="en-US" sz="1400" b="1"><a:solidFill><a:srgbClr val="2A8FA0"/></a:solidFill><a:latin typeface="Microsoft YaHei" panose="020B0503020204020204" pitchFamily="34" charset="-122"/></a:endParaRPr></a:p></p:txBody></p:sp></p:spTree></p:cSld><p:clrMapOvr><a:masterClrMapping/></p:clrMapOvr><mc:AlternateContent xmlns:mc="http://schemas.openxmlformats.org/markup-compatibility/2006" xmlns:p14="http://schemas.microsoft.com/office/powerpoint/2010/main"><mc:Choice Requires="p14"><p:transition spd="slow" p14:dur="2000" advTm="16792"/></mc:Choice><mc:Fallback xmlns=""><p:transition spd="slow" advTm="16792"/></mc:Fallback></mc:AlternateContent></p:sld>